{
  "sections": [],
  "variants": [
    {
      "paths": [
        "/documentation/appintents/app-shortcuts"
      ],
      "traits": [
        {
          "interfaceLanguage": "swift"
        }
      ]
    }
  ],
  "topicSections": [
    {
      "identifiers": [
        "doc://com.apple.AppIntents/documentation/AppIntents/AppShortcutsProvider"
      ],
      "anchor": "App-Shortcut-management",
      "title": "App Shortcut management"
    },
    {
      "identifiers": [
        "doc://com.apple.AppIntents/documentation/AppIntents/AppShortcut",
        "doc://com.apple.AppIntents/documentation/AppIntents/AppShortcutPhrase",
        "doc://com.apple.AppIntents/documentation/AppIntents/NegativeAppShortcutPhrase",
        "doc://com.apple.AppIntents/documentation/AppIntents/NegativeAppShortcutPhrases",
        "doc://com.apple.documentation/documentation/BundleResources/Information-Property-List/CFBundleIcons/CFBundlePrimaryIcon/NSAppIconActionTintColorName",
        "doc://com.apple.documentation/documentation/BundleResources/Information-Property-List/CFBundleIcons/CFBundlePrimaryIcon/NSAppIconComplementingColorNames",
        "doc://com.apple.AppIntents/documentation/AppIntents/AppShortcutsBuilder",
        "doc://com.apple.AppIntents/documentation/AppIntents/ShortcutTileColor"
      ],
      "anchor": "App-Shortcut-definition",
      "title": "App Shortcut definition"
    },
    {
      "identifiers": [
        "doc://com.apple.AppIntents/documentation/AppIntents/AppShortcutOptionsCollection",
        "doc://com.apple.AppIntents/documentation/AppIntents/AppShortcutOptionsCollectionProtocol",
        "doc://com.apple.AppIntents/documentation/AppIntents/AppShortcutOptionsCollectionSpecification",
        "doc://com.apple.AppIntents/documentation/AppIntents/AppShortcutOptionsCollectionSpecificationBuilder"
      ],
      "anchor": "App-Shortcut-options",
      "title": "App Shortcut options"
    },
    {
      "identifiers": [
        "doc://com.apple.AppIntents/documentation/AppIntents/AppShortcutParameterPresentation",
        "doc://com.apple.AppIntents/documentation/AppIntents/AppShortcutParameterPresentationSummary",
        "doc://com.apple.AppIntents/documentation/AppIntents/AppShortcutParameterPresentationSummaryString",
        "doc://com.apple.AppIntents/documentation/AppIntents/AppShortcutParameterPresentationTitle",
        "doc://com.apple.AppIntents/documentation/AppIntents/AppShortcutParameterPresentationTitleString"
      ],
      "anchor": "App-Shortcut-parameter-presentation",
      "title": "App Shortcut parameter presentation"
    },
    {
      "identifiers": [
        "doc://com.apple.AppIntents/documentation/AppIntents/ShortcutsUIButton",
        "doc://com.apple.AppIntents/documentation/AppIntents/ShortcutsLink",
        "doc://com.apple.AppIntents/documentation/AppIntents/ShortcutsLinkStyle"
      ],
      "anchor": "Buttons",
      "title": "Buttons"
    },
    {
      "identifiers": [
        "doc://com.apple.AppIntents/documentation/AppIntents/SiriTipUIView",
        "doc://com.apple.AppIntents/documentation/AppIntents/SiriTipView",
        "doc://com.apple.AppIntents/documentation/AppIntents/SiriTipViewStyle"
      ],
      "anchor": "Tip-views",
      "title": "Tip views"
    }
  ],
  "primaryContentSections": [
    {
      "content": [
        {
          "text": "Overview",
          "level": 2,
          "anchor": "Overview",
          "type": "heading"
        },
        {
          "inlineContent": [
            {
              "text": "Starting with iOS 15 and macOS 13, you can create a preconfigured App Shortcut that enables people to discover and run your app intent without any configuration. By creating App Shortcuts, you make your app’s functionality instantly available for use in Shortcuts, Spotlight, and Siri from the moment a person installs your app — without any setup in the Shortcuts app or an Add to Siri button. On iPhone models that support the Action button, people can associate your preconfigured App Shortcut on the Action button for quick access of your app’s functionality.",
              "type": "text"
            }
          ],
          "type": "paragraph"
        },
        {
          "style": "note",
          "name": "Note",
          "content": [
            {
              "inlineContent": [
                {
                  "type": "text",
                  "text": "Apple may extract anonymized App Shortcuts data such as localized"
                },
                {
                  "type": "text",
                  "text": " "
                },
                {
                  "type": "text",
                  "text": "phrases, display representation values, and the title and description of"
                },
                {
                  "type": "text",
                  "text": " "
                },
                {
                  "type": "text",
                  "text": "related intents. Machine learning models use this data when training to help"
                },
                {
                  "type": "text",
                  "text": " "
                },
                {
                  "type": "text",
                  "text": "improve the App Shortcuts experience."
                }
              ],
              "type": "paragraph"
            }
          ],
          "type": "aside"
        },
        {
          "inlineContent": [
            {
              "type": "text",
              "text": "Key app functionalities that people use to complete a task quickly and that you expose to the system with app intents are great candidates for App Shortcuts. For each high-value app intent, create an App Shortcut that specifies the intended action, the required parameters, the spoken phrases someone uses to run it, and the short title and the image that appear in the Shortcuts app."
            }
          ],
          "type": "paragraph"
        },
        {
          "inlineContent": [
            {
              "text": "To offer an App Shortcut:",
              "type": "text"
            }
          ],
          "type": "paragraph"
        },
        {
          "items": [
            {
              "content": [
                {
                  "type": "paragraph",
                  "inlineContent": [
                    {
                      "text": "Create an app intent for a key app functionality as described in ",
                      "type": "text"
                    },
                    {
                      "identifier": "doc://com.apple.AppIntents/documentation/AppIntents/Creating-your-first-app-intent",
                      "isActive": true,
                      "type": "reference"
                    },
                    {
                      "type": "text",
                      "text": "."
                    }
                  ]
                }
              ]
            },
            {
              "content": [
                {
                  "type": "paragraph",
                  "inlineContent": [
                    {
                      "text": "Create the ",
                      "type": "text"
                    },
                    {
                      "isActive": true,
                      "type": "reference",
                      "identifier": "doc://com.apple.AppIntents/documentation/AppIntents/AppShortcut"
                    },
                    {
                      "text": " object for your app intent using the ",
                      "type": "text"
                    },
                    {
                      "isActive": true,
                      "type": "reference",
                      "identifier": "doc://com.apple.AppIntents/documentation/AppIntents/AppShortcut/init(intent:phrases:shortTitle:systemImageName:)-2hk1x"
                    },
                    {
                      "text": " initializer with phrases people can use to run the app intent and with the metadata that appears in the Shortcuts app.",
                      "type": "text"
                    }
                  ]
                }
              ]
            },
            {
              "content": [
                {
                  "inlineContent": [
                    {
                      "text": "Implement the ",
                      "type": "text"
                    },
                    {
                      "isActive": true,
                      "identifier": "doc://com.apple.AppIntents/documentation/AppIntents/AppShortcutsProvider",
                      "type": "reference"
                    },
                    {
                      "text": " protocol that provides the App Shortcuts you offer to the Shortcuts app.",
                      "type": "text"
                    }
                  ],
                  "type": "paragraph"
                }
              ]
            }
          ],
          "type": "orderedList"
        },
        {
          "inlineContent": [
            {
              "type": "text",
              "text": "With these three steps, you make your app’s functionality more discoverable and enable people to interact with your app in a lightweight way. However, the system displays a default interface for your App Shortcut. To display a custom view for each shortcut, return a SwiftUI view in your app intent’s "
            },
            {
              "identifier": "doc://com.apple.AppIntents/documentation/AppIntents/AppIntent/perform()",
              "type": "reference",
              "isActive": true
            },
            {
              "type": "text",
              "text": " method."
            }
          ],
          "type": "paragraph"
        },
        {
          "style": "note",
          "name": "Related sessions from WWDC22",
          "content": [
            {
              "inlineContent": [
                {
                  "type": "text",
                  "text": ""
                },
                {
                  "identifier": "https://developer.apple.com/videos/play/wwdc2022/10170",
                  "type": "reference",
                  "isActive": true
                },
                {
                  "type": "text",
                  "text": " and "
                },
                {
                  "identifier": "https://developer.apple.com/videos/play/wwdc2022/10169",
                  "type": "reference",
                  "isActive": true
                },
                {
                  "type": "text",
                  "text": "."
                }
              ],
              "type": "paragraph"
            }
          ],
          "type": "aside"
        },
        {
          "text": "Offer App Shortcuts with preconfigured parameters",
          "level": 2,
          "anchor": "Offer-App-Shortcuts-with-preconfigured-parameters",
          "type": "heading"
        },
        {
          "inlineContent": [
            {
              "text": "With App Shortcuts, you can also preconfigure phrases for app intents that use specific parameters. When you include parameters, people can use one phrase to start an interaction with an app without Siri having to ask for clarification. For example, a meditation app could offer an app intent to start a meditation with the phrase “Start a meditation”. Because the app offers many different meditations, Siri would require an additional clarification which meditation a person wants to start.",
              "type": "text"
            }
          ],
          "type": "paragraph"
        },
        {
          "inlineContent": [
            {
              "text": "With an App Shortcut, you can supply preconfigured parameters ahead of time that enable a person to skip this clarification step. For example, the meditation app could provide parameterized phrases where each phrase represents a common meditation. A person could then start a meditation with one phrase like “Start a mindfulness meditation.” or “Start a short meditation.”",
              "type": "text"
            }
          ],
          "type": "paragraph"
        },
        {
          "text": "Make your App Shortcuts even more discoverable",
          "level": 2,
          "anchor": "Make-your-App-Shortcuts-even-more-discoverable",
          "type": "heading"
        },
        {
          "inlineContent": [
            {
              "type": "text",
              "text": "Although App Shortcuts don’t require a person to do any configuration in the Shortcuts app or by using the Add to Siri button, you may want to present elements in your app to tell people about an available App Shortcut. You have two options:"
            }
          ],
          "type": "paragraph"
        },
        {
          "items": [
            {
              "content": [
                {
                  "inlineContent": [
                    {
                      "identifier": "doc://com.apple.AppIntents/documentation/AppIntents/SiriTipView",
                      "isActive": true,
                      "type": "reference"
                    },
                    {
                      "type": "text",
                      "text": " and "
                    },
                    {
                      "identifier": "doc://com.apple.AppIntents/documentation/AppIntents/SiriTipUIView",
                      "isActive": true,
                      "type": "reference"
                    },
                    {
                      "type": "text",
                      "text": " present a view that tells a person that an App Shortcut is available."
                    }
                  ],
                  "type": "paragraph"
                }
              ]
            },
            {
              "content": [
                {
                  "inlineContent": [
                    {
                      "identifier": "doc://com.apple.AppIntents/documentation/AppIntents/ShortcutsLink",
                      "isActive": true,
                      "type": "reference"
                    },
                    {
                      "text": " enables you to display a link to your App Shortcut.",
                      "type": "text"
                    }
                  ],
                  "type": "paragraph"
                }
              ]
            }
          ],
          "type": "unorderedList"
        },
        {
          "inlineContent": [
            {
              "code": "ShortcutsLink",
              "type": "codeVoice"
            },
            {
              "text": " is especially convenient if your app displays a list of its available App Shortcuts.",
              "type": "text"
            }
          ],
          "type": "paragraph"
        }
      ],
      "kind": "content"
    }
  ],
  "seeAlsoSections": [
    {
      "generated": true,
      "identifiers": [
        "doc://com.apple.AppIntents/documentation/AppIntents/app-intents",
        "doc://com.apple.AppIntents/documentation/AppIntents/intent-discovery"
      ],
      "anchor": "Actions",
      "title": "Actions"
    }
  ],
  "metadata": {
    "title": "App Shortcuts",
    "roleHeading": "API Collection",
    "role": "collectionGroup",
    "modules": [
      {
        "name": "App Intents"
      }
    ]
  },
  "schemaVersion": {
    "major": 0,
    "minor": 3,
    "patch": 0
  },
  "kind": "article",
  "abstract": [
    {
      "type": "text",
      "text": "Integrate your app’s intents and entities with the Shortcuts app, Siri, Spotlight, and the Action button on supported iPhone and Apple Watch models."
    }
  ],
  "identifier": {
    "url": "doc://com.apple.AppIntents/documentation/AppIntents/app-shortcuts",
    "interfaceLanguage": "swift"
  },
  "hierarchy": {
    "paths": [
      [
        "doc://com.apple.documentation/documentation/technologies",
        "doc://com.apple.AppIntents/documentation/AppIntents"
      ]
    ]
  },
  "references": {
    "doc://com.apple.AppIntents/documentation/AppIntents": {
      "role": "collection",
      "identifier": "doc://com.apple.AppIntents/documentation/AppIntents",
      "abstract": [
        {
          "type": "text",
          "text": "Make your app’s content and actions discoverable with system experiences like Spotlight, widgets, and the Shortcuts app."
        }
      ],
      "kind": "symbol",
      "url": "https://developer.apple.com/documentation/appintents",
      "type": "topic",
      "title": "App Intents"
    },
    "doc://com.apple.AppIntents/documentation/AppIntents/ShortcutTileColor": {
      "navigatorTitle": [
        {
          "text": "ShortcutTileColor",
          "kind": "identifier"
        }
      ],
      "kind": "symbol",
      "url": "https://developer.apple.com/documentation/appintents/shortcuttilecolor",
      "title": "ShortcutTileColor",
      "type": "topic",
      "role": "symbol",
      "identifier": "doc://com.apple.AppIntents/documentation/AppIntents/ShortcutTileColor",
      "fragments": [
        {
          "text": "enum",
          "kind": "keyword"
        },
        {
          "text": " ",
          "kind": "text"
        },
        {
          "text": "ShortcutTileColor",
          "kind": "identifier"
        }
      ],
      "abstract": [
        {
          "text": "Describes the colors a shortcut tile in the Shortcuts app.",
          "type": "text"
        }
      ]
    },
    "doc://com.apple.AppIntents/documentation/AppIntents/ShortcutsLinkStyle": {
      "navigatorTitle": [
        {
          "text": "ShortcutsLinkStyle",
          "kind": "identifier"
        }
      ],
      "title": "ShortcutsLinkStyle",
      "fragments": [
        {
          "text": "struct",
          "kind": "keyword"
        },
        {
          "text": " ",
          "kind": "text"
        },
        {
          "text": "ShortcutsLinkStyle",
          "kind": "identifier"
        }
      ],
      "url": "https://developer.apple.com/documentation/appintents/shortcutslinkstyle",
      "type": "topic",
      "abstract": [
        {
          "type": "text",
          "text": "The styles to apply to buttons you use to open your app’s page in the Shortcuts app."
        }
      ],
      "kind": "symbol",
      "identifier": "doc://com.apple.AppIntents/documentation/AppIntents/ShortcutsLinkStyle",
      "role": "symbol"
    },
    "doc://com.apple.AppIntents/documentation/AppIntents/SiriTipUIView": {
      "kind": "symbol",
      "navigatorTitle": [
        {
          "kind": "identifier",
          "text": "SiriTipUIView"
        }
      ],
      "fragments": [
        {
          "kind": "keyword",
          "text": "class"
        },
        {
          "kind": "text",
          "text": " "
        },
        {
          "kind": "identifier",
          "text": "SiriTipUIView"
        }
      ],
      "identifier": "doc://com.apple.AppIntents/documentation/AppIntents/SiriTipUIView",
      "title": "SiriTipUIView",
      "role": "symbol",
      "url": "https://developer.apple.com/documentation/appintents/siritipuiview",
      "type": "topic",
      "abstract": [
        {
          "text": "A view that displays the phrase a person uses to invoke an App Shortcut.",
          "type": "text"
        }
      ]
    },
    "doc://com.apple.AppIntents/documentation/AppIntents/AppShortcutParameterPresentationSummary": {
      "url": "https://developer.apple.com/documentation/appintents/appshortcutparameterpresentationsummary",
      "role": "symbol",
      "title": "AppShortcutParameterPresentationSummary",
      "fragments": [
        {
          "kind": "keyword",
          "text": "struct"
        },
        {
          "kind": "text",
          "text": " "
        },
        {
          "kind": "identifier",
          "text": "AppShortcutParameterPresentationSummary"
        }
      ],
      "type": "topic",
      "identifier": "doc://com.apple.AppIntents/documentation/AppIntents/AppShortcutParameterPresentationSummary",
      "navigatorTitle": [
        {
          "kind": "identifier",
          "text": "AppShortcutParameterPresentationSummary"
        }
      ],
      "abstract": [
        {
          "text": "The summary of the presentation of an App Shortcut parameter.",
          "type": "text"
        }
      ],
      "kind": "symbol"
    },
    "doc://com.apple.AppIntents/documentation/AppIntents/AppShortcut": {
      "navigatorTitle": [
        {
          "kind": "identifier",
          "text": "AppShortcut"
        }
      ],
      "abstract": [
        {
          "type": "text",
          "text": "A type that defines a preconfigured shortcut for a specific app intent."
        }
      ],
      "type": "topic",
      "kind": "symbol",
      "role": "symbol",
      "fragments": [
        {
          "kind": "keyword",
          "text": "struct"
        },
        {
          "kind": "text",
          "text": " "
        },
        {
          "kind": "identifier",
          "text": "AppShortcut"
        }
      ],
      "url": "https://developer.apple.com/documentation/appintents/appshortcut",
      "title": "AppShortcut",
      "identifier": "doc://com.apple.AppIntents/documentation/AppIntents/AppShortcut"
    },
    "https://developer.apple.com/videos/play/wwdc2022/10170": {
      "titleInlineContent": [
        {
          "text": "Session 10170: Implement App Shortcuts with App Intents",
          "type": "text"
        }
      ],
      "url": "https://developer.apple.com/videos/play/wwdc2022/10170",
      "type": "link",
      "identifier": "https://developer.apple.com/videos/play/wwdc2022/10170",
      "title": "Session 10170: Implement App Shortcuts with App Intents"
    },
    "https://developer.apple.com/videos/play/wwdc2022/10169": {
      "titleInlineContent": [
        {
          "type": "text",
          "text": "Session 10169: Design App Shortcuts"
        }
      ],
      "title": "Session 10169: Design App Shortcuts",
      "url": "https://developer.apple.com/videos/play/wwdc2022/10169",
      "identifier": "https://developer.apple.com/videos/play/wwdc2022/10169",
      "type": "link"
    },
    "doc://com.apple.AppIntents/documentation/AppIntents/AppShortcutOptionsCollectionSpecification": {
      "role": "symbol",
      "identifier": "doc://com.apple.AppIntents/documentation/AppIntents/AppShortcutOptionsCollectionSpecification",
      "abstract": [],
      "kind": "symbol",
      "url": "https://developer.apple.com/documentation/appintents/appshortcutoptionscollectionspecification",
      "type": "topic",
      "navigatorTitle": [
        {
          "text": "AppShortcutOptionsCollectionSpecification",
          "kind": "identifier"
        }
      ],
      "fragments": [
        {
          "text": "protocol",
          "kind": "keyword"
        },
        {
          "text": " ",
          "kind": "text"
        },
        {
          "text": "AppShortcutOptionsCollectionSpecification",
          "kind": "identifier"
        }
      ],
      "title": "AppShortcutOptionsCollectionSpecification"
    },
    "doc://com.apple.AppIntents/documentation/AppIntents/AppShortcutParameterPresentationTitleString": {
      "navigatorTitle": [
        {
          "text": "AppShortcutParameterPresentationTitleString",
          "kind": "identifier"
        }
      ],
      "kind": "symbol",
      "deprecated": true,
      "url": "https://developer.apple.com/documentation/appintents/appshortcutparameterpresentationtitlestring",
      "title": "AppShortcutParameterPresentationTitleString",
      "type": "topic",
      "role": "symbol",
      "identifier": "doc://com.apple.AppIntents/documentation/AppIntents/AppShortcutParameterPresentationTitleString",
      "fragments": [
        {
          "text": "struct",
          "kind": "keyword"
        },
        {
          "text": " ",
          "kind": "text"
        },
        {
          "text": "AppShortcutParameterPresentationTitleString",
          "kind": "identifier"
        }
      ],
      "abstract": []
    },
    "doc://com.apple.AppIntents/documentation/AppIntents/AppShortcutParameterPresentationTitle": {
      "type": "topic",
      "identifier": "doc://com.apple.AppIntents/documentation/AppIntents/AppShortcutParameterPresentationTitle",
      "abstract": [
        {
          "text": "A struct that represents the title of the presentation of an App Shortcut.",
          "type": "text"
        }
      ],
      "role": "symbol",
      "deprecated": true,
      "title": "AppShortcutParameterPresentationTitle",
      "navigatorTitle": [
        {
          "text": "AppShortcutParameterPresentationTitle",
          "kind": "identifier"
        }
      ],
      "fragments": [
        {
          "text": "struct",
          "kind": "keyword"
        },
        {
          "text": " ",
          "kind": "text"
        },
        {
          "text": "AppShortcutParameterPresentationTitle",
          "kind": "identifier"
        }
      ],
      "url": "https://developer.apple.com/documentation/appintents/appshortcutparameterpresentationtitle",
      "kind": "symbol"
    },
    "doc://com.apple.AppIntents/documentation/AppIntents/AppShortcutsProvider": {
      "fragments": [
        {
          "text": "protocol",
          "kind": "keyword"
        },
        {
          "text": " ",
          "kind": "text"
        },
        {
          "text": "AppShortcutsProvider",
          "kind": "identifier"
        }
      ],
      "abstract": [
        {
          "type": "text",
          "text": "A type alias for the type that provides an app’s preconfigured shortcuts."
        }
      ],
      "title": "AppShortcutsProvider",
      "url": "https://developer.apple.com/documentation/appintents/appshortcutsprovider",
      "navigatorTitle": [
        {
          "text": "AppShortcutsProvider",
          "kind": "identifier"
        }
      ],
      "identifier": "doc://com.apple.AppIntents/documentation/AppIntents/AppShortcutsProvider",
      "type": "topic",
      "kind": "symbol",
      "role": "symbol"
    },
    "doc://com.apple.AppIntents/documentation/AppIntents/ShortcutsLink": {
      "role": "symbol",
      "identifier": "doc://com.apple.AppIntents/documentation/AppIntents/ShortcutsLink",
      "abstract": [
        {
          "type": "text",
          "text": "A button that brings users to the current app’s App Shortcuts page in the Shortcuts app."
        }
      ],
      "kind": "symbol",
      "url": "https://developer.apple.com/documentation/appintents/shortcutslink",
      "type": "topic",
      "navigatorTitle": [
        {
          "kind": "identifier",
          "text": "ShortcutsLink"
        }
      ],
      "fragments": [
        {
          "kind": "keyword",
          "text": "struct"
        },
        {
          "kind": "text",
          "text": " "
        },
        {
          "kind": "identifier",
          "text": "ShortcutsLink"
        }
      ],
      "title": "ShortcutsLink"
    },
    "doc://com.apple.AppIntents/documentation/AppIntents/NegativeAppShortcutPhrase": {
      "type": "topic",
      "navigatorTitle": [
        {
          "kind": "identifier",
          "text": "NegativeAppShortcutPhrase"
        }
      ],
      "identifier": "doc://com.apple.AppIntents/documentation/AppIntents/NegativeAppShortcutPhrase",
      "url": "https://developer.apple.com/documentation/appintents/negativeappshortcutphrase",
      "kind": "symbol",
      "abstract": [
        {
          "text": "An object that represents a negative phrase.",
          "type": "text"
        }
      ],
      "role": "symbol",
      "fragments": [
        {
          "kind": "keyword",
          "text": "struct"
        },
        {
          "kind": "text",
          "text": " "
        },
        {
          "kind": "identifier",
          "text": "NegativeAppShortcutPhrase"
        }
      ],
      "title": "NegativeAppShortcutPhrase"
    },
    "doc://com.apple.AppIntents/documentation/AppIntents/AppShortcut/init(intent:phrases:shortTitle:systemImageName:)-2hk1x": {
      "fragments": [
        {
          "kind": "identifier",
          "text": "init"
        },
        {
          "kind": "text",
          "text": "<"
        },
        {
          "kind": "genericParameter",
          "text": "Intent"
        },
        {
          "kind": "text",
          "text": ">("
        },
        {
          "kind": "externalParam",
          "text": "intent"
        },
        {
          "kind": "text",
          "text": ": "
        },
        {
          "kind": "typeIdentifier",
          "text": "Intent"
        },
        {
          "kind": "text",
          "text": ", "
        },
        {
          "kind": "externalParam",
          "text": "phrases"
        },
        {
          "kind": "text",
          "text": ": ["
        },
        {
          "preciseIdentifier": "s:10AppIntents0A14ShortcutPhraseV",
          "kind": "typeIdentifier",
          "text": "AppShortcutPhrase"
        },
        {
          "kind": "text",
          "text": "<"
        },
        {
          "kind": "typeIdentifier",
          "text": "Intent"
        },
        {
          "kind": "text",
          "text": ">], "
        },
        {
          "kind": "externalParam",
          "text": "shortTitle"
        },
        {
          "kind": "text",
          "text": ": "
        },
        {
          "preciseIdentifier": "s:10Foundation23LocalizedStringResourceV",
          "kind": "typeIdentifier",
          "text": "LocalizedStringResource"
        },
        {
          "kind": "text",
          "text": "?, "
        },
        {
          "kind": "externalParam",
          "text": "systemImageName"
        },
        {
          "kind": "text",
          "text": ": "
        },
        {
          "preciseIdentifier": "s:SS",
          "kind": "typeIdentifier",
          "text": "String"
        },
        {
          "kind": "text",
          "text": "?)"
        }
      ],
      "title": "init(intent:phrases:shortTitle:systemImageName:)",
      "abstract": [
        {
          "type": "text",
          "text": "Initializes an App Shortcut with phrases that run the app intent, a title, and an image."
        }
      ],
      "deprecated": true,
      "kind": "symbol",
      "identifier": "doc://com.apple.AppIntents/documentation/AppIntents/AppShortcut/init(intent:phrases:shortTitle:systemImageName:)-2hk1x",
      "url": "https://developer.apple.com/documentation/appintents/appshortcut/init(intent:phrases:shorttitle:systemimagename:)-2hk1x",
      "role": "symbol",
      "type": "topic"
    },
    "doc://com.apple.AppIntents/documentation/AppIntents/AppShortcutsBuilder": {
      "fragments": [
        {
          "text": "enum",
          "kind": "keyword"
        },
        {
          "text": " ",
          "kind": "text"
        },
        {
          "text": "AppShortcutsBuilder",
          "kind": "identifier"
        }
      ],
      "abstract": [
        {
          "text": "A result builder that allows you to declaratively describe the App Shortcuts that your app provides.",
          "type": "text"
        }
      ],
      "kind": "symbol",
      "role": "symbol",
      "title": "AppShortcutsBuilder",
      "type": "topic",
      "navigatorTitle": [
        {
          "text": "AppShortcutsBuilder",
          "kind": "identifier"
        }
      ],
      "identifier": "doc://com.apple.AppIntents/documentation/AppIntents/AppShortcutsBuilder",
      "url": "https://developer.apple.com/documentation/appintents/appshortcutsbuilder"
    },
    "doc://com.apple.AppIntents/documentation/AppIntents/AppShortcutOptionsCollectionSpecificationBuilder": {
      "role": "symbol",
      "identifier": "doc://com.apple.AppIntents/documentation/AppIntents/AppShortcutOptionsCollectionSpecificationBuilder",
      "abstract": [],
      "kind": "symbol",
      "url": "https://developer.apple.com/documentation/appintents/appshortcutoptionscollectionspecificationbuilder",
      "type": "topic",
      "navigatorTitle": [
        {
          "text": "AppShortcutOptionsCollectionSpecificationBuilder",
          "kind": "identifier"
        }
      ],
      "fragments": [
        {
          "text": "enum",
          "kind": "keyword"
        },
        {
          "text": " ",
          "kind": "text"
        },
        {
          "text": "AppShortcutOptionsCollectionSpecificationBuilder",
          "kind": "identifier"
        }
      ],
      "title": "AppShortcutOptionsCollectionSpecificationBuilder"
    },
    "doc://com.apple.AppIntents/documentation/AppIntents/AppShortcutOptionsCollectionProtocol": {
      "role": "symbol",
      "identifier": "doc://com.apple.AppIntents/documentation/AppIntents/AppShortcutOptionsCollectionProtocol",
      "abstract": [],
      "kind": "symbol",
      "url": "https://developer.apple.com/documentation/appintents/appshortcutoptionscollectionprotocol",
      "type": "topic",
      "navigatorTitle": [
        {
          "text": "AppShortcutOptionsCollectionProtocol",
          "kind": "identifier"
        }
      ],
      "fragments": [
        {
          "text": "protocol",
          "kind": "keyword"
        },
        {
          "text": " ",
          "kind": "text"
        },
        {
          "text": "AppShortcutOptionsCollectionProtocol",
          "kind": "identifier"
        }
      ],
      "title": "AppShortcutOptionsCollectionProtocol"
    },
    "doc://com.apple.AppIntents/documentation/AppIntents/AppShortcutParameterPresentationSummaryString": {
      "abstract": [],
      "identifier": "doc://com.apple.AppIntents/documentation/AppIntents/AppShortcutParameterPresentationSummaryString",
      "title": "AppShortcutParameterPresentationSummaryString",
      "url": "https://developer.apple.com/documentation/appintents/appshortcutparameterpresentationsummarystring",
      "type": "topic",
      "kind": "symbol",
      "role": "symbol",
      "navigatorTitle": [
        {
          "text": "AppShortcutParameterPresentationSummaryString",
          "kind": "identifier"
        }
      ],
      "fragments": [
        {
          "text": "struct",
          "kind": "keyword"
        },
        {
          "text": " ",
          "kind": "text"
        },
        {
          "text": "AppShortcutParameterPresentationSummaryString",
          "kind": "identifier"
        }
      ]
    },
    "doc://com.apple.AppIntents/documentation/AppIntents/AppShortcutOptionsCollection": {
      "navigatorTitle": [
        {
          "text": "AppShortcutOptionsCollection",
          "kind": "identifier"
        }
      ],
      "fragments": [
        {
          "text": "struct",
          "kind": "keyword"
        },
        {
          "text": " ",
          "kind": "text"
        },
        {
          "text": "AppShortcutOptionsCollection",
          "kind": "identifier"
        }
      ],
      "url": "https://developer.apple.com/documentation/appintents/appshortcutoptionscollection",
      "kind": "symbol",
      "role": "symbol",
      "abstract": [
        {
          "text": "Represents a collection of options for parameters of an App Shortcut.",
          "type": "text"
        }
      ],
      "type": "topic",
      "identifier": "doc://com.apple.AppIntents/documentation/AppIntents/AppShortcutOptionsCollection",
      "title": "AppShortcutOptionsCollection"
    },
    "doc://com.apple.AppIntents/documentation/AppIntents/intent-discovery": {
      "role": "collectionGroup",
      "abstract": [
        {
          "text": "Donate your app’s intents to the system to help it identify trends and predict",
          "type": "text"
        },
        {
          "text": " ",
          "type": "text"
        },
        {
          "text": "future behaviors.",
          "type": "text"
        }
      ],
      "type": "topic",
      "title": "Intent discovery",
      "kind": "article",
      "url": "https://developer.apple.com/documentation/appintents/intent-discovery",
      "identifier": "doc://com.apple.AppIntents/documentation/AppIntents/intent-discovery"
    },
    "doc://com.apple.AppIntents/documentation/AppIntents/SiriTipView": {
      "type": "topic",
      "title": "SiriTipView",
      "url": "https://developer.apple.com/documentation/appintents/siritipview",
      "abstract": [
        {
          "text": "A SwiftUI view that displays the phrase someone uses to invoke an App Shortcut.",
          "type": "text"
        }
      ],
      "role": "symbol",
      "fragments": [
        {
          "kind": "keyword",
          "text": "struct"
        },
        {
          "kind": "text",
          "text": " "
        },
        {
          "kind": "identifier",
          "text": "SiriTipView"
        }
      ],
      "identifier": "doc://com.apple.AppIntents/documentation/AppIntents/SiriTipView",
      "navigatorTitle": [
        {
          "kind": "identifier",
          "text": "SiriTipView"
        }
      ],
      "kind": "symbol"
    },
    "doc://com.apple.AppIntents/documentation/AppIntents/AppShortcutParameterPresentation": {
      "title": "AppShortcutParameterPresentation",
      "fragments": [
        {
          "text": "struct",
          "kind": "keyword"
        },
        {
          "text": " ",
          "kind": "text"
        },
        {
          "text": "AppShortcutParameterPresentation",
          "kind": "identifier"
        }
      ],
      "abstract": [
        {
          "type": "text",
          "text": "Describes the presentation of an App Shortcut  for the provided parameter."
        }
      ],
      "identifier": "doc://com.apple.AppIntents/documentation/AppIntents/AppShortcutParameterPresentation",
      "type": "topic",
      "kind": "symbol",
      "role": "symbol",
      "url": "https://developer.apple.com/documentation/appintents/appshortcutparameterpresentation",
      "navigatorTitle": [
        {
          "text": "AppShortcutParameterPresentation",
          "kind": "identifier"
        }
      ]
    },
    "doc://com.apple.AppIntents/documentation/AppIntents/Creating-your-first-app-intent": {
      "url": "https://developer.apple.com/documentation/appintents/creating-your-first-app-intent",
      "role": "article",
      "title": "Creating your first app intent",
      "type": "topic",
      "identifier": "doc://com.apple.AppIntents/documentation/AppIntents/Creating-your-first-app-intent",
      "abstract": [
        {
          "type": "text",
          "text": "Create your first app intent that makes your app available in system experiences like Spotlight or the Shortcuts app."
        }
      ],
      "kind": "article"
    },
    "doc://com.apple.AppIntents/documentation/AppIntents/AppIntent/perform()": {
      "url": "https://developer.apple.com/documentation/appintents/appintent/perform()",
      "role": "symbol",
      "required": true,
      "title": "perform()",
      "fragments": [
        {
          "text": "func",
          "kind": "keyword"
        },
        {
          "kind": "text",
          "text": " "
        },
        {
          "text": "perform",
          "kind": "identifier"
        },
        {
          "text": "() ",
          "kind": "text"
        },
        {
          "text": "async",
          "kind": "keyword"
        },
        {
          "text": " ",
          "kind": "text"
        },
        {
          "text": "throws",
          "kind": "keyword"
        },
        {
          "text": " -> ",
          "kind": "text"
        },
        {
          "text": "Self",
          "kind": "typeIdentifier"
        },
        {
          "text": ".",
          "kind": "text"
        },
        {
          "text": "PerformResult",
          "preciseIdentifier": "s:10AppIntents0A6IntentP13PerformResultQa",
          "kind": "typeIdentifier"
        }
      ],
      "type": "topic",
      "identifier": "doc://com.apple.AppIntents/documentation/AppIntents/AppIntent/perform()",
      "defaultImplementations": 6,
      "abstract": [
        {
          "type": "text",
          "text": "Performs the intent after resolving the provided parameters."
        }
      ],
      "kind": "symbol"
    },
    "doc://com.apple.AppIntents/documentation/AppIntents/AppShortcutPhrase": {
      "type": "topic",
      "url": "https://developer.apple.com/documentation/appintents/appshortcutphrase",
      "identifier": "doc://com.apple.AppIntents/documentation/AppIntents/AppShortcutPhrase",
      "title": "AppShortcutPhrase",
      "kind": "symbol",
      "fragments": [
        {
          "text": "struct",
          "kind": "keyword"
        },
        {
          "text": " ",
          "kind": "text"
        },
        {
          "text": "AppShortcutPhrase",
          "kind": "identifier"
        }
      ],
      "abstract": [
        {
          "text": "A spoken phrase that causes the system to run the corresponding App Shortcut.",
          "type": "text"
        }
      ],
      "navigatorTitle": [
        {
          "text": "AppShortcutPhrase",
          "kind": "identifier"
        }
      ],
      "role": "symbol"
    },
    "doc://com.apple.documentation/documentation/BundleResources/Information-Property-List/CFBundleIcons/CFBundlePrimaryIcon/NSAppIconComplementingColorNames": {
      "title": "NSAppIconComplementingColorNames",
      "url": "https://developer.apple.com/documentation/BundleResources/Information-Property-List/CFBundleIcons/CFBundlePrimaryIcon/NSAppIconComplementingColorNames",
      "type": "topic",
      "abstract": [
        {
          "text": "The names of the colors to use for the background of the App Shortcuts platter.",
          "type": "text"
        }
      ],
      "kind": "symbol",
      "identifier": "doc://com.apple.documentation/documentation/BundleResources/Information-Property-List/CFBundleIcons/CFBundlePrimaryIcon/NSAppIconComplementingColorNames",
      "role": "symbol"
    },
    "doc://com.apple.documentation/documentation/technologies": {
      "role": "overview",
      "identifier": "doc://com.apple.documentation/documentation/technologies",
      "abstract": [
        {
          "type": "text",
          "text": ""
        }
      ],
      "kind": "technologies",
      "url": "https://developer.apple.com/documentation/technologies",
      "type": "topic",
      "title": "Technologies"
    },
    "doc://com.apple.AppIntents/documentation/AppIntents/NegativeAppShortcutPhrases": {
      "type": "topic",
      "url": "https://developer.apple.com/documentation/appintents/negativeappshortcutphrases",
      "identifier": "doc://com.apple.AppIntents/documentation/AppIntents/NegativeAppShortcutPhrases",
      "kind": "symbol",
      "navigatorTitle": [
        {
          "text": "NegativeAppShortcutPhrases",
          "kind": "identifier"
        }
      ],
      "fragments": [
        {
          "text": "struct",
          "kind": "keyword"
        },
        {
          "text": " ",
          "kind": "text"
        },
        {
          "text": "NegativeAppShortcutPhrases",
          "kind": "identifier"
        }
      ],
      "abstract": [
        {
          "type": "text",
          "text": "This is a set of negative phrases, which will all be added to the app-level negative"
        },
        {
          "type": "text",
          "text": " "
        },
        {
          "type": "text",
          "text": "training set. All the training data specified here, will be used to completely bypass your app"
        }
      ],
      "title": "NegativeAppShortcutPhrases",
      "role": "symbol"
    },
    "doc://com.apple.AppIntents/documentation/AppIntents/ShortcutsUIButton": {
      "role": "symbol",
      "fragments": [
        {
          "kind": "keyword",
          "text": "class"
        },
        {
          "kind": "text",
          "text": " "
        },
        {
          "kind": "identifier",
          "text": "ShortcutsUIButton"
        }
      ],
      "abstract": [
        {
          "text": "A button that opens the current app’s page in the Shortcuts app.",
          "type": "text"
        }
      ],
      "type": "topic",
      "title": "ShortcutsUIButton",
      "kind": "symbol",
      "url": "https://developer.apple.com/documentation/appintents/shortcutsuibutton",
      "navigatorTitle": [
        {
          "kind": "identifier",
          "text": "ShortcutsUIButton"
        }
      ],
      "identifier": "doc://com.apple.AppIntents/documentation/AppIntents/ShortcutsUIButton"
    },
    "doc://com.apple.documentation/documentation/BundleResources/Information-Property-List/CFBundleIcons/CFBundlePrimaryIcon/NSAppIconActionTintColorName": {
      "type": "topic",
      "kind": "symbol",
      "identifier": "doc://com.apple.documentation/documentation/BundleResources/Information-Property-List/CFBundleIcons/CFBundlePrimaryIcon/NSAppIconActionTintColorName",
      "role": "symbol",
      "url": "https://developer.apple.com/documentation/BundleResources/Information-Property-List/CFBundleIcons/CFBundlePrimaryIcon/NSAppIconActionTintColorName",
      "abstract": [
        {
          "type": "text",
          "text": "The tint color to apply to text and symbols in the App Shortcuts platter."
        }
      ],
      "title": "NSAppIconActionTintColorName"
    },
    "doc://com.apple.AppIntents/documentation/AppIntents/app-intents": {
      "abstract": [
        {
          "type": "text",
          "text": "Define the custom actions your app exposes to the system, and incorporate"
        },
        {
          "type": "text",
          "text": " "
        },
        {
          "type": "text",
          "text": "support for existing SiriKit intents."
        }
      ],
      "title": "App intents",
      "url": "https://developer.apple.com/documentation/appintents/app-intents",
      "identifier": "doc://com.apple.AppIntents/documentation/AppIntents/app-intents",
      "type": "topic",
      "kind": "article",
      "role": "collectionGroup"
    },
    "doc://com.apple.AppIntents/documentation/AppIntents/SiriTipViewStyle": {
      "role": "symbol",
      "navigatorTitle": [
        {
          "kind": "identifier",
          "text": "SiriTipViewStyle"
        }
      ],
      "title": "SiriTipViewStyle",
      "url": "https://developer.apple.com/documentation/appintents/siritipviewstyle",
      "abstract": [
        {
          "type": "text",
          "text": "The styles to apply to the tip views you use to display spoken phrases."
        }
      ],
      "identifier": "doc://com.apple.AppIntents/documentation/AppIntents/SiriTipViewStyle",
      "fragments": [
        {
          "kind": "keyword",
          "text": "struct"
        },
        {
          "kind": "text",
          "text": " "
        },
        {
          "kind": "identifier",
          "text": "SiriTipViewStyle"
        }
      ],
      "kind": "symbol",
      "type": "topic"
    }
  },
  "diffAvailability": {
    "major": {
      "change": "modified",
      "platform": "Xcode",
      "versions": [
        "16.0",
        "16.3"
      ]
    }
  },
  "legalNotices": {
    "copyright": "Copyright &copy; 2025 Apple Inc. All rights reserved.",
    "termsOfUse": "https://www.apple.com/legal/internet-services/terms/site.html",
    "privacyPolicy": "https://www.apple.com/privacy/privacy-policy"
  }
}
